passtodict/__init__.py
passtodict-0.1.4.dist-info/LICENSE
passtodict-0.1.4.dist-info/METADATA
passtodict-0.1.4.dist-info/WHEEL
passtodict-0.1.4.dist-info/entry_points.txt
passtodict-0.1.4.dist-info/top_level.txt
passtodict-0.1.4.dist-info/RECORD
