Metadata-Version: 2.1
Name: passtodict
Version: 0.1.4
Summary: Password-Store client library
Home-page: https://gitlab.com/pacholik1/Pass2Dict
Author: Vojtěch Pachol
Author-email: pacholick@gmail.com
License: LGPL-3.0
Keywords: pass
Platform: UNKNOWN
Classifier: Development Status :: 4 - Beta
Classifier: Programming Language :: Python :: 3
Requires-Dist: python-gnupg
